py_mcp_travelplanner/cli.py
py_mcp_travelplanner/cli_handlers.py
py_mcp_travelplanner/config.py
py_mcp_travelplanner/control_server.py
py_mcp_travelplanner/mcp_server.py
py_mcp_travelplanner/event_server/event_server.py
py_mcp_travelplanner/event_server/main.py
py_mcp_travelplanner/finance_server/finance_server.py
py_mcp_travelplanner/finance_server/main.py
py_mcp_travelplanner/flight_server/flight_server.py
py_mcp_travelplanner/flight_server/main.py
py_mcp_travelplanner/geocoder_server/geocoder_server.py
py_mcp_travelplanner/geocoder_server/main.py
py_mcp_travelplanner/hotel_server/hotel_server.py
py_mcp_travelplanner/hotel_server/main.py
py_mcp_travelplanner/weather_server/main.py
py_mcp_travelplanner/weather_server/weather_server.py
py_mcp_travelplanner/weather_server/weatherstack_server.py
py_mcp_travelplanner-0.1.20.dist-info/licenses/LICENSE
py_mcp_travelplanner-0.1.20.dist-info/METADATA
py_mcp_travelplanner-0.1.20.dist-info/WHEEL
py_mcp_travelplanner-0.1.20.dist-info/entry_points.txt
py_mcp_travelplanner-0.1.20.dist-info/top_level.txt
py_mcp_travelplanner-0.1.20.dist-info/RECORD
