Metadata-Version: 2.4
Name: py_mcp_travelplanner
Version: 0.1.20
Summary: Minimal Azure Policy engine with file and sdk backends
Author: leonard Avevor
License: MIT
Project-URL: Homepage, https://py_mc_travelplanner.io/
Project-URL: Source, https://github.com/leonavevor/mcp_travelassistant.git
Project-URL: Documentation, https://github.com/leonavevor/mcp_travelassistant/blob/main/README.md
Project-URL: QuickStart, https://github.com/leonavevor/mcp_travelassistant/blob/main/QUICKSTART.md
Requires-Python: <4.0,>=3.11.1
License-File: LICENSE
Requires-Dist: requests==2.32.3
Requires-Dist: pytest==8.2
Requires-Dist: tox==4.32.0
Requires-Dist: pre-commit==3.4.0
Requires-Dist: pyyaml>=6.0.1
Requires-Dist: python-dotenv>=1.1.0
Requires-Dist: mcp>=1.9.1
Requires-Dist: fastmcp>=2.5.1
Provides-Extra: ci-build
Requires-Dist: setuptools>=61.0; extra == "ci-build"
Requires-Dist: poetry_core>=1.0.0; extra == "ci-build"
Requires-Dist: wheel; extra == "ci-build"
Requires-Dist: build>=0.10.0; extra == "ci-build"
Provides-Extra: servers
Requires-Dist: fastmcp>=2.5.1; extra == "servers"
Requires-Dist: mcp>=1.9.1; extra == "servers"
Requires-Dist: requests==2.32.3; extra == "servers"
Requires-Dist: geopy>=2.4.1; extra == "servers"
Requires-Dist: nominatim>=0.1; extra == "servers"
Requires-Dist: ratelimiter>=1.2.0.post0; extra == "servers"
Requires-Dist: python-dotenv>=1.1.0; extra == "servers"
Requires-Dist: typing-extensions>=4.13.2; extra == "servers"
Provides-Extra: event-server
Requires-Dist: fastmcp>=2.5.1; extra == "event-server"
Requires-Dist: mcp>=1.9.1; extra == "event-server"
Requires-Dist: requests==2.32.3; extra == "event-server"
Provides-Extra: finance-server
Requires-Dist: fastmcp>=2.5.1; extra == "finance-server"
Requires-Dist: mcp>=1.9.1; extra == "finance-server"
Requires-Dist: requests==2.32.3; extra == "finance-server"
Provides-Extra: flight-server
Requires-Dist: fastmcp>=2.5.1; extra == "flight-server"
Requires-Dist: mcp>=1.9.1; extra == "flight-server"
Requires-Dist: requests==2.32.3; extra == "flight-server"
Provides-Extra: geocoder-server
Requires-Dist: fastmcp>=2.5.1; extra == "geocoder-server"
Requires-Dist: geopy>=2.4.1; extra == "geocoder-server"
Requires-Dist: mcp>=1.9.1; extra == "geocoder-server"
Requires-Dist: nominatim>=0.1; extra == "geocoder-server"
Requires-Dist: ratelimiter>=1.2.0.post0; extra == "geocoder-server"
Requires-Dist: requests==2.32.3; extra == "geocoder-server"
Provides-Extra: hotel-server
Requires-Dist: fastmcp>=2.5.1; extra == "hotel-server"
Requires-Dist: mcp>=1.9.1; extra == "hotel-server"
Requires-Dist: python-dotenv>=1.1.0; extra == "hotel-server"
Requires-Dist: requests==2.32.3; extra == "hotel-server"
Provides-Extra: weather-server
Requires-Dist: fastmcp>=2.5.1; extra == "weather-server"
Requires-Dist: mcp>=1.9.1; extra == "weather-server"
Requires-Dist: requests==2.32.3; extra == "weather-server"
Requires-Dist: typing-extensions>=4.13.2; extra == "weather-server"
Dynamic: license-file
